autohelper/AutoHelper.py
autohelper/__init__.py
autohelper/capture/BaseCaptureMethod.py
autohelper/capture/HwndWindow.py
autohelper/capture/__init__.py
autohelper/capture/adb/ADBCaptureMethod.py
autohelper/capture/adb/DeviceManager.py
autohelper/capture/adb/__init__.py
autohelper/capture/adb/targets.py
autohelper/capture/adb/vbox.py
autohelper/capture/adb/bin/__init__.py
autohelper/capture/windows/WindowsGraphicsCaptureMethod.py
autohelper/capture/windows/__init__.py
autohelper/capture/windows/d3d11.py
autohelper/capture/windows/utils.py
autohelper/capture/windows/window.py
autohelper/color/Color.py
autohelper/color/__init__.py
autohelper/config/Config.py
autohelper/config/InfoDict.py
autohelper/config/__init__.py
autohelper/feature/Box.py
autohelper/feature/Feature.py
autohelper/feature/FeatureSet.py
autohelper/feature/FindFeature.py
autohelper/feature/__init__.py
autohelper/gui/App.py
autohelper/gui/Communicate.py
autohelper/gui/MainWindow.py
autohelper/gui/TabTitles.py
autohelper/gui/__init__.py
autohelper/gui/resources.py
autohelper/gui/debug/AspectRatioWidget.py
autohelper/gui/debug/DebugTab.py
autohelper/gui/debug/FrameWidget.py
autohelper/gui/debug/InfoWidget.py
autohelper/gui/debug/LoggerWidget.py
autohelper/gui/debug/__init__.py
autohelper/gui/i18n/__init__.py
autohelper/gui/i18n/path.py
autohelper/gui/icon/__init__.py
autohelper/gui/icon/icon.py
autohelper/gui/loading/LoadingWindow.py
autohelper/gui/loading/__init__.py
autohelper/gui/overlay/OverlayWindow.py
autohelper/gui/overlay/__init__.py
autohelper/gui/tasks/ConfigItemFactory.py
autohelper/gui/tasks/StartButton.py
autohelper/gui/tasks/TaskOpButton.py
autohelper/gui/tasks/TaskTab.py
autohelper/gui/tasks/TooltipTableWidget.py
autohelper/gui/tasks/__init__.py
autohelper/gui/util/Alert.py
autohelper/gui/util/InitWorker.py
autohelper/gui/util/__init__.py
autohelper/gui/widget/ListTableWidgetItem.py
autohelper/gui/widget/NumericTableWidgetItem.py
autohelper/gui/widget/RoundCornerContainer.py
autohelper-0.0.7.dist-info/METADATA
autohelper-0.0.7.dist-info/WHEEL
autohelper-0.0.7.dist-info/top_level.txt
autohelper-0.0.7.dist-info/RECORD
