Metadata-Version: 2.1
Name: autohelper
Version: 0.0.7
Summary: Automation with Computer Vision for Python
Home-page: https://github.com/CrashTechnologyOfficer/autoui
Author: CTO
Author-email: firedcto@gmail.com
Classifier: Programming Language :: Python :: 3
Classifier: Intended Audience :: Developers
Classifier: License :: OSI Approved :: MIT License
Classifier: Operating System :: Microsoft :: Windows
Requires-Python: >=3.4
Requires-Dist: adbutils ==2.2.1
Requires-Dist: numpy ~=1.26.4
Requires-Dist: PyDirectInput ~=1.0.4
Requires-Dist: pywin32 ==306
Requires-Dist: typing-extensions ~=4.10.0
Requires-Dist: PySide6 ~=6.6.2
